trakt/__init__.py
trakt/__version__.py
trakt/calendar.py
trakt/core.py
trakt/errors.py
trakt/mixins.py
trakt/movies.py
trakt/people.py
trakt/sync.py
trakt/tv.py
trakt/users.py
trakt/utils.py
pytraktcdm-3.4.25.dist-info/LICENSE
pytraktcdm-3.4.25.dist-info/METADATA
pytraktcdm-3.4.25.dist-info/WHEEL
pytraktcdm-3.4.25.dist-info/top_level.txt
pytraktcdm-3.4.25.dist-info/RECORD
