Metadata-Version: 2.1
Name: pytraktcdm
Version: 3.4.25
Summary: Pythonic abstraction layer for easier scripting of the Trakt.tv REST API.
Home-page: https://github.com/chrisdma/python-pytrakt
Author: Chris Martinez
Author-email: chris@chrismartinez.net
License: Apache 2.0
Classifier: Development Status :: 5 - Production/Stable
Classifier: Intended Audience :: Developers
Classifier: Natural Language :: English
Classifier: License :: Freely Distributable
Classifier: Programming Language :: Python
Classifier: Programming Language :: Python :: 3
Classifier: Programming Language :: Python :: 3.6
Classifier: Programming Language :: Python :: 3.7
Classifier: Programming Language :: Python :: 3.8
Classifier: Programming Language :: Python :: 3.9
License-File: LICENSE
Requires-Dist: deprecated ~=1.2.13
Requires-Dist: requests-oauthlib >=1.3
Requires-Dist: requests >=2.25
Requires-Dist: dataclasses ; python_version < "3.7"
